{
  "_format": "hh-sol-cache-2",
  "files": {
    "/Users/keertimehta/Desktop/HackerRamp/contracts/RentalAgreement.sol": {
      "lastModificationDate": 1739009851088,
      "contentHash": "5f37304950e4a83ec478cb5593a02bf6",
      "sourceName": "contracts/RentalAgreement.sol",
      "solcConfig": {
        "version": "0.8.18",
        "settings": {
          "optimizer": {
            "enabled": false,
            "runs": 200
          },
          "outputSelection": {
            "*": {
              "*": [
                "abi",
                "evm.bytecode",
                "evm.deployedBytecode",
                "evm.methodIdentifiers",
                "metadata"
              ],
              "": [
                "ast"
              ]
            }
          }
        }
      },
      "imports": [],
      "versionPragmas": [
        "^0.8.18"
      ],
      "artifacts": [
        "RentalAgreement"
      ]
    }
  }
}
